<?xml version="1.0" encoding="utf-8"?>

<resources>

  <string-array name="unitGrid">
     <item name="meter">Метри</item>
     <item name="yard">Ярдове</item>
  </string-array>

  <string-array name="wallsType">
     <item name="none">Изключени</item>
     <item name="convex">Вдлъбнати</item>
  </string-array>

  <string-array name="zoomCtrl">
     <item name="0">Изключени</item>
     <item name="1">Временни</item>
     <item name="2">Постоянни</item>
  </string-array>

  <string-array name="stationNames">
     <item name="alpha">С букви и цифри</item>
     <item name="number">С цифри</item>
  </string-array>
  
  <!-- UNUSED string-array name="extend_name">
     <item>Наляво</item>
     <item>Вертикално</item>
     <item>Надясно</item>
     <item>- -</item>
  </string-array -->

  <!-- number values must agree with TopoDroidConst constants DISTOX_EXPORT_XXX 
  <string-array name="exportShots">
     <item name="therion">Therion</item>
     <item name="compass">Compass</item>
     <item name="csurvey">cSurvey</item>
     <item name="pockettoopo">PocketTopo</item>
     <item name="survex">Survex</item>
     <item name="visualtopo">VisualTopo</item>
     <item name="walls">Walls</item>
     <item name="csv">CSV</item>
     <item name="dxf">DXF</item>
  </string-array>
  -->
  <!-- number values must agree with TopoDroidConst constants DISTOX_EXPORT_XXX
  <string-array name="exportSketch">
     <item name="therion">Therion</item>
     <item name="csurvey">cSurvey</item>
     <item name="dxf">DXF</item>
     <item name="png">PNG</item>
     <item name="svg">SVG</item>
  </string-array>
  -->

  <string-array name="legShots">
     <item name="two">2</item>
     <item name="three">3</item>
     <item name="four">4</item>
  </string-array>

  <string-array name="extraButtons">
     <item name="basic">Базови</item>
     <item name="normal">Нормални</item>
     <item name="advanced">Пълни</item>
     <item name="experimental">Експериментални</item>
     <!-- item name="complete">Complete</item -->
  </string-array>

  <string-array name="sizeButtons">
     <item name="small1">Малки</item>
     <item name="large">Големи</item>
  </string-array>

  <string-array name="logStream">
     <item name="android">Системен лог</item>
     <item name="file">Файлов лог</item>
  </string-array>

  <string-array name="connMode">
     <item name="batch">Ръчна</item>
     <item name="continuous">Постоянна</item>
  </string-array>

  <!-- UNUSED string-array name="altitudeType">
    <item name="wgs84">WGS84 елипсоидна</item>
    <item name="asl">Ортометрична</item>
  </string-array -->

  <string-array name="sockType">
     <item name="default">Стандартен</item>
     <item name="Insecure">Без парола</item>
  </string-array>

  <string-array name="surveyStations">
     <item name="no">Изключени</item>
     <item name="for">Странични, права отсечка</item>
     <item name="back">Странични, обратна отсечка</item>
     <item name="for2">Права отсечка, странични</item>
     <item name="back2">Обратна отсечка, странични</item>
     <item name="anomaly">Обратна отсечка, странични, права</item>
  </string-array>

  <string-array name="pickerType">
     <item name="recent">Последни използвани</item>
     <item name="list">Списък</item>
     <item name="grid">Таблица</item>
  </string-array>

  <!-- UNUSED string-array name="deviceType">
     <item name="none">Няма</item>
     <item name="A3">A3</item>
     <item name="X310">X310</item>
  </string-array -->

  <string-array name="deviceBT">
     <item name="0">Изключен</item>
     <item name="1">Проверка при старт</item>
     <item name="2">Включен</item>
  </string-array>

  <!-- UNUSED string-array name="exportType">
     <item name="th">Therion</item>
     <item name="dat">Compass</item>
     <item name="svx">Survex</item>
     <item name="tro">VisualTopo</item>
  </string-array -->

  <string-array name="lineStyle">
     <item name="none">Фини</item>
     <item name="two">Нормални</item>
     <item name="two">Груби</item>
     <item name="bezier">"Безие" криви</item>
  </string-array>

  <string-array name="groupBy">
     <item name="distance">Разстояние</item>
     <item name="four">Групи по четири</item>
     <item name="only16">Само първите 16</item>
  </string-array>

  <string-array name="unitLength">
     <item name="meters">Метри</item>
     <item name="feet">Футове</item>
  </string-array>

  <string-array name="unitAngle">
     <item name="degrees">Градуси</item>
     <item name="grads">Гради</item>
  </string-array>

  <string-array name="unitLocation">
     <item name="degrees">градуси</item>
     <item name="ddmmss">градуси, минути, секунди</item>
  </string-array>

  <string-array name="calibAlgo">
     <item name="auto">Автоматичен</item>
     <item name="linear">Линеен</item>
     <item name="nonlinear">Нелинеен</item>
  </string-array>

</resources>
