<?xml version="1.0" encoding="utf-8"?>

<resources>

  <!-- FIXME string-array name="unitGrid">
     <item name="meter">Mètres</item>
     <item name="yard">Yards</item>
     <item name="two_tf">2 feet</item>
  </string-array -->


  <string-array name="survexEol">
     <item name="lf">Linux</item>
     <item name="lfcr">Windows</item>
  </string-array>


  <string-array name="wallsType">
     <item name="none">Aucun</item>
     <item name="convex">Convexe</item>
  </string-array>


  <string-array name="acadVersion">
     <item name="9">AutoCAD 6</item>
     <item name="13">AutoCAD 12</item>
  </string-array>


  <string-array name="zoomCtrl">
     <item name="0">OFF, Désactivé</item>
     <item name="1">Temporaire</item>
     <item name="2">Permanent</item>
  </string-array>
  

  <string-array name="stationNames">
     <item name="alpha">Alphanumerique</item>
     <item name="number">Numérique</item>
  </string-array>
 

  <!-- UNUSED string-array name="extend_name">
     <item>Left</item>
     <item>Vertical</item>
     <item>Right</item>
     <item>None</item>
  </string-array -->


  <string-array name="legShots">
     <item name="two">2</item>
     <item name="three">3</item>
     <item name="four">4</item>
  </string-array>

  <string-array name="exportShots">
     <item name="none">Aucun</item>
     <item name="therion">Therion</item>
     <item name="compass">Compass</item>
     <!-- item name="csurvey">cSurvey</item -->
     <item name="pockettopo">PocketTopo</item>
     <item name="polygon">Polygon</item>
     <item name="survex">Survex</item>
     <item name="topo">Topo</item>
     <item name="visualtopo">VisualTopo</item>
     <item name="walls">Walls</item>
     <item name="csv">CSV</item>
     <item name="dxf">DXF</item>
  </string-array>

  <string-array name="exportPlot">
     <item name="none">Aucun</item>
     <item name="therion">Therion</item>
     <item name="csurvey">cSurvey</item>
     <item name="dxf">DXF</item>
     <item name="svg">SVG</item>
     <item name="png">PNG</item>
  </string-array>

  <string-array name="extraButtons">
     <item name="basic">Basique</item>
     <item name="normal">Normal</item>
     <item name="advanced">Avancé</item>
     <item name="expert">Expérimental</item>
     <!-- item name="complete">Complete</item -->
  </string-array>
 

  <!-- TODO string-array name="sizeButtons">
     <item name="small">Petit</item>
     <item name="normal">Normal</item>
     <item name="medium">Medium</item>
     <item name="large">Grand</item>
     <item name="huge">Huge</item>
  </string-array -->
 

  <string-array name="logStream">
     <item name="android">Journal système</item>
     <item name="file">Journal fichiers</item>
  </string-array>


  <string-array name="connMode">
     <item name="batch">À la demande, par lots</item>
     <item name="continuous">Continue</item>
  </string-array>
 

  <!-- UNUSED string-array name="altitudeType">
    <item name="wgs84">Ellipsoide WGS84</item>
    <item name="asl">Orthometrique</item>
  </string-array -->
  
  <string-array name="sectionStations">
     <item name="both">Les deux</item>
     <item name="from">Derrière</item>
     <item name="to">Devant</item>
  </string-array>
 

  <string-array name="sockType">
     <item name="default">Par défaut</item>
     <item name="Insecure">Non sécurisé</item>
     <!-- item name="Port">Port</item -->
     <!-- item name="InsecurePort">Insecure/Port</item -->
  </string-array>


  <string-array name="surveyStations">
     <item name="no">Désactivé</item>
     <item name="for">Visée normale, visées latérales en premier</item>
     <item name="back">Visée inverse, visées latérales en premier</item>
     <item name="for2">Visée normale, cheminement en premier</item>
     <item name="back2">Visée inverse, cheminement en premier</item>
     <item name="anomaly">Visée Arrière, Backsight</item>
     <item name="tripod">Tripod</item>
  </string-array>
 

   <string-array name="pickerType">
     <item name="recent">Plus récentes</item>
     <item name="list">Liste</item>
     <item name="grid">Grille</item>
     <item name="grid3">Triple grid</item>
   </string-array>


  <!-- UNUSED string-array name="deviceType">
     <item name="none">Aucune</item>
     <item name="A3">A3</item>
     <item name="X310">X310</item>
  </string-array -->
 
  <string-array name="deviceBT">
     <item name="0">Désactivé</item>
     <item name="1">Vérifier au démarrage</item>
     <item name="2">Activé</item>
  </string-array>
  

 <!-- UNUSED string-array name="exportType">
     <item name="th">Therion</item>
     <item name="dat">Compass</item>
     <item name="svx">Survex</item>
     <item name="tro">VisualTopo</item>
  </string-array -->

  <string-array name="lineStyle">
     <item name="none">Fine</item>
     <item name="two">Normale</item>
     <item name="three">Grossière</item>
     <item name="bezier">Bézier</item>
  </string-array>

  <string-array name="groupBy">
     <item name="distance">Distance</item>
     <item name="four">Quatre en même temps</item>
     <item name="only16">Seize premières</item>
  </string-array>

  <string-array name="unitLength">
     <item name="meters">Mètres</item>
     <item name="feet">Pieds</item>
  </string-array>

  <string-array name="unitAngle">
     <item name="degrees">Degrés décimaux</item>
     <item name="grads">Grades décimaux</item>
  </string-array>

  <string-array name="unitLocation">
     <item name="degrees">Degrés décimaux</item>
     <item name="ddmmss">Degrés, minutes, secondes</item>
  </string-array>


  <string-array name="calibAlgo">
     <item name="auto">Automatique</item>
     <item name="linear">Linéaire</item>
     <item name="nonlinear">Non-linéaire</item>
  </string-array>

</resources>
